[
  {
    "part": "Amarakosha - Kanda 1",
    "freq": {
      "्": 3179,
      "ा": 1952,
      "र": 1635,
      "त": 1294,
      "ि": 1218,
      "व": 954,
      "न": 934,
      "स": 929,
      "म": 926,
      "क": 812,
      "ु": 756,
      "ः": 732,
      "य": 712,
      "प": 679,
      "द": 673,
      "ो": 614,
      "श": 493,
      "ी": 449,
      "ं": 441,
      "े": 412,
      "ल": 408,
      "ष": 371,
      "ग": 335,
      "च": 318,
      "ण": 294,
      "ह": 294,
      "भ": 283,
      "ध": 269,
      "ज": 216,
      "ौ": 141,
      "ृ": 135,
      "ब": 133,
      "ू": 122,
      "थ": 115,
      "ऽ": 111,
      "ङ": 103,
      "ड": 89,
      "ै": 89,
      "अ": 85,
      "ट": 81,
      "ञ": 62,
      "ठ": 62,
      "ख": 57,
      "घ": 52,
      "उ": 39,
      "आ": 33,
      "छ": 26,
      "इ": 23,
      "फ": 12,
      "ढ": 9,
      "ऋ": 7,
      "झ": 7,
      "ए": 4,
      "ऊ": 4,
      "ई": 3,
      "ऐ": 2,
      "औ": 1
    }
  },
  {
    "part": "Amarakosha - Kanda 2",
    "freq": {
      "्": 8256,
      "ा": 4807,
      "र": 3887,
      "त": 3221,
      "क": 2718,
      "ि": 2709,
      "स": 2434,
      "य": 2180,
      "न": 2115,
      "व": 2097,
      "म": 2062,
      "ु": 1955,
      "प": 1834,
      "ः": 1524,
      "द": 1412,
      "ो": 1393,
      "ी": 1295,
      "ल": 1286,
      "ं": 1130,
      "े": 1124,
      "श": 1046,
      "ग": 908,
      "ष": 908,
      "ण": 814,
      "च": 800,
      "ध": 666,
      "ज": 647,
      "ह": 619,
      "भ": 512,
      "ू": 454,
      "ृ": 453,
      "थ": 431,
      "ट": 411,
      "ौ": 407,
      "ब": 367,
      "ऽ": 275,
      "ङ": 268,
      "ड": 238,
      "ै": 192,
      "ख": 158,
      "ञ": 156,
      "अ": 154,
      "घ": 109,
      "फ": 103,
      "छ": 96,
      "ठ": 88,
      "आ": 80,
      "उ": 65,
      "ऋ": 44,
      "इ": 36,
      "ढ": 26,
      "ए": 15,
      "झ": 14,
      "ऊ": 9,
      "ओ": 6,
      "ऐ": 2,
      "औ": 2,
      "ई": 1
    }
  },
  {
    "part": "Amarakosha - Kanda 3",
    "freq": {
      "्": 3881,
      "ा": 1811,
      "र": 1758,
      "त": 1598,
      "ि": 1504,
      "न": 1087,
      "य": 1087,
      "स": 1018,
      "व": 1009,
      "े": 1001,
      "प": 960,
      "क": 925,
      "म": 843,
      "ु": 761,
      "द": 691,
      "ः": 577,
      "ो": 561,
      "ष": 501,
      "ं": 488,
      "श": 444,
      "ग": 399,
      "ल": 394,
      "च": 370,
      "ण": 346,
      "ौ": 325,
      "ध": 303,
      "ी": 292,
      "भ": 289,
      "ऽ": 262,
      "ह": 255,
      "ू": 250,
      "ृ": 239,
      "ज": 227,
      "थ": 160,
      "ब": 134,
      "ट": 134,
      "ङ": 123,
      "ख": 76,
      "अ": 75,
      "घ": 69,
      "ड": 67,
      "ठ": 64,
      "ञ": 57,
      "छ": 55,
      "ै": 48,
      "आ": 40,
      "उ": 39,
      "इ": 37,
      "फ": 28,
      "ढ": 19,
      "ए": 6,
      "ऋ": 3,
      "ऊ": 2,
      "झ": 1,
      "ई": 1,
      "ओ": 1,
      "औ": 1
    }
  },
  {
    "part": "Amarakosha - Full",
    "freq": {
      "्": 15316,
      "ा": 8570,
      "र": 7280,
      "त": 6113,
      "ि": 5431,
      "क": 4455,
      "स": 4381,
      "न": 4136,
      "व": 4060,
      "य": 3979,
      "म": 3831,
      "प": 3473,
      "ु": 3472,
      "ः": 2833,
      "द": 2776,
      "ो": 2568,
      "े": 2537,
      "ल": 2088,
      "ं": 2059,
      "ी": 2036,
      "श": 1983,
      "ष": 1780,
      "ग": 1642,
      "च": 1488,
      "ण": 1454,
      "ध": 1238,
      "ह": 1168,
      "ज": 1090,
      "भ": 1084,
      "ौ": 873,
      "ृ": 827,
      "ू": 826,
      "थ": 706,
      "ऽ": 648,
      "ब": 634,
      "ट": 626,
      "ङ": 494,
      "ड": 394,
      "ै": 329,
      "अ": 314,
      "ख": 291,
      "ञ": 275,
      "घ": 230,
      "ठ": 214,
      "छ": 177,
      "आ": 153,
      "उ": 143,
      "फ": 143,
      "इ": 96,
      "ऋ": 54,
      "ढ": 54,
      "ए": 25,
      "झ": 22,
      "ऊ": 15,
      "ओ": 7,
      "ई": 5,
      "ऐ": 4,
      "औ": 4
    }
  }
]